{
    "man": [
        { "name": "Mermaid L.S.", "file": "mp_bea_tat_m_000", "id": "MP_Bea_M_LArm_001", "dlc": "mpbeach" },
        { "name": "Tiki Tower", "file": "mp_bea_tat_m_007", "id": "MP_Bea_M_LArm_000", "dlc": "mpbeach"  },
        { "name": "$100 Bill", "file": "mp_bus_tat_m_001", "id": "MP_Buis_M_LeftArm_000", "dlc": "mpbusiness" },
        { "name": "All-Seeing Eye", "file": "mp_bus_tat_m_010", "id": "MP_Buis_M_LeftArm_001", "dlc": "mpbusiness" }
    ],
    "woman": [
        { "name": "Tribal Flower", "file": "mp_bea_tat_f_002", "id": "MP_Bea_F_LArm_000", "dlc": "mpbeach" },
        { "name": "Parrot", "file": "mp_bea_tat_f_015", "id": "MP_Bea_F_LArm_001", "dlc": "mpbeach" },
        { "name": "Greed is Good", "file": "mp_bus_tat_f_010", "id": "MP_Buis_F_LArm_000", "dlc": "mpbusiness" }
    ],
    "shared": [
        { "name": "Skull Rider", "file": "mp_xm2_tat_m_000", "manId": "MP_Xmas2_M_Tat_000", "womanId": "MP_Xmas2_F_Tat_000", "dlc": "mpchristmas2" },
        { "name": "Electric Snake", "file": "mp_xm2_tat_m_010", "manId": "MP_Xmas2_M_Tat_010", "womanId": "MP_Xmas2_F_Tat_010", "dlc": "mpchristmas2" },
        { "name": "8 Ball Skull", "file": "mp_xm2_tat_m_012", "manId": "MP_Xmas2_M_Tat_012", "womanId": "MP_Xmas2_F_Tat_012", "dlc": "mpchristmas2" },
        { "name": "Time's Up Outline", "file": "mp_xm2_tat_m_020", "manId": "MP_Xmas2_M_Tat_020", "womanId": "MP_Xmas2_F_Tat_020", "dlc": "mpchristmas2" },
        { "name": "Time's Up Color", "file": "mp_xm2_tat_m_021", "manId": "MP_Xmas2_M_Tat_021", "womanId": "MP_Xmas2_F_Tat_021", "dlc": "mpchristmas2" },
        { "name": "Toxic Trails", "file": "mp_airraces_tattoo_003", "manId": "MP_Airraces_Tattoo_003_M", "womanId": "MP_Airraces_Tattoo_003_F", "dlc": "mpairraces" },
        { "name": "Urban Stunter", "file": "mp_biker_tat_012", "manId": "MP_MP_Biker_Tat_012_M", "womanId": "MP_MP_Biker_Tat_012_F", "dlc": "mpbiker" },
        { "name": "Macabre Tree", "file": "mp_biker_tat_016", "manId": "'MP_MP_Biker_Tat_016_M", "womanId": "MP_MP_Biker_Tat_016_F", "dlc": "mpbiker" },
        { "name": "Cranial Rose", "file": "mp_biker_tat_020", "manId": "MP_MP_Biker_Tat_020_M", "womanId": "MP_MP_Biker_Tat_020_F", "dlc": "mpbiker" },
        { "name": "Live To Ride", "file": "mp_biker_tat_024", "manId": "MP_MP_Biker_Tat_024_M", "womanId": "MP_MP_Biker_Tat_024_F", "dlc": "mpbiker" },
        { "name": "Good Luck", "file": "mp_biker_tat_025", "manId": "MP_MP_Biker_Tat_025_M", "womanId": "MP_MP_Biker_Tat_025_F", "dlc": "mpbiker" },
        { "name": "Chain Fist", "file": "mp_biker_tat_035", "manId": "MP_MP_Biker_Tat_035_M", "womanId": "MP_MP_Biker_Tat_035_F", "dlc": "mpbiker" },
        { "name": "Ride Hard Die Fast", "file": "mp_biker_tat_045", "manId": "MP_MP_Biker_Tat_045_M", "womanId": "MP_MP_Biker_Tat_045_F", "dlc": "mpbiker" },
        { "name": "Muffler Helmet", "file": "mp_biker_tat_053", "manId": "MP_MP_Biker_Tat_053_M", "womanId": "MP_MP_Biker_Tat_053_F", "dlc": "mpbiker" },
        { "name": "Poison Scorpion", "file": "mp_biker_tat_055", "manId": "MP_MP_Biker_Tat_055_M", "womanId": "MP_MP_Biker_Tat_055_F", "dlc": "mpbiker" },
        { "name": "Viking Warrior", "file": "mp_christmas2017_tattoo_001", "manId": "MP_Christmas2017_Tattoo_001_M", "womanId": "MP_Christmas2017_Tattoo_001_F", "dlc": "mpchristmas2017" },
        { "name": "Tiger & Mask", "file": "mp_christmas2017_tattoo_004", "manId": "MP_Christmas2017_Tattoo_004_M", "womanId": "MP_Christmas2017_Tattoo_004_F", "dlc": "mpchristmas2017" },
        { "name": "Spartan Combat", "file": "mp_christmas2017_tattoo_007", "manId": "MP_Christmas2017_Tattoo_007_M", "womanId": "MP_Christmas2017_Tattoo_007_F", "dlc": "mpchristmas2017" },
        { "name": "Katana", "file": "mp_christmas2017_tattoo_013", "manId": "MP_Christmas2017_Tattoo_013_M", "womanId": "MP_Christmas2017_Tattoo_013_F", "dlc": "mpchristmas2017" },
        { "name": "Winged Serpent", "file": "mp_christmas2017_tattoo_025", "manId": "MP_Christmas2017_Tattoo_025_M", "womanId": "MP_Christmas2017_Tattoo_025_F", "dlc": "mpchristmas2017" },
        { "name": "Cerberus", "file": "mp_christmas2017_tattoo_029", "manId": "MP_Christmas2017_Tattoo_029_M", "womanId": "MP_Christmas2017_Tattoo_029_F", "dlc": "mpchristmas2017" },
        { "name": "Serpents", "file": "mp_fm_tat_005", "manId": "FM_Tat_M_005", "womanId": "FM_Tat_F_005", "dlc": "basegame" },
        { "name": "Oriental Mural", "file": "mp_fm_tat_006", "manId": "FM_Tat_M_006", "womanId": "FM_Tat_F_006", "dlc": "basegame" },
        { "name": "Zodiac Skull", "file": "mp_fm_tat_015", "manId": "FM_Tat_M_015", "womanId": "FM_Tat_F_015", "dlc": "basegame" },
        { "name": "Lady M", "file": "mp_fm_tat_031", "manId": "FM_Tat_M_031", "womanId": "FM_Tat_F_031", "dlc": "basegame" },
        { "name": "Dope Skull", "file": "mp_fm_tat_041", "manId": "FM_Tat_M_041", "womanId": "FM_Tat_F_041", "dlc": "basegame" },
        { "name": "Burning Heart", "file": "mp_fm_tat_award_001", "manId": "FM_Tat_Award_M_001", "womanId": "FM_Tat_Award_F_001", "dlc": "basegame" },
        { "name": "Racing Blonde", "file": "mp_fm_tat_award_007", "manId": "FM_Tat_Award_M_007", "womanId": "FM_Tat_Award_F_007", "dlc": "basegame" },
        { "name": "Racing Brunette", "file": "mp_fm_tat_award_015", "manId": "FM_Tat_Award_M_015", "womanId": "FM_Tat_Award_F_015", "dlc": "basegame" },
        { "name": "Sidearm", "file": "mp_gunrunning_tattoo_004", "manId": "MP_Gunrunning_Tattoo_004_M", "womanId": "MP_Gunrunning_Tattoo_004_F", "dlc": "mpgunrunning" },
        { "name": "Bandolier", "file": "mp_gunrunning_tattoo_008", "manId": "MP_Gunrunning_Tattoo_008_M", "womanId": "MP_Gunrunning_Tattoo_008_F", "dlc": "mpgunrunning" },
        { "name": "Spiked Skull", "file": "mp_gunrunning_tattoo_015", "manId": "MP_Gunrunning_Tattoo_015_M", "womanId": "MP_Gunrunning_Tattoo_015_F", "dlc": "mpgunrunning" },
        { "name": "Blood Money", "file": "mp_gunrunning_tattoo_016", "manId": "MP_Gunrunning_Tattoo_016_M", "womanId": "MP_Gunrunning_Tattoo_016_F", "dlc": "mpgunrunning" },
        { "name": "Praying Skull", "file": "mp_gunrunning_tattoo_025", "manId": "MP_Gunrunning_Tattoo_025_M", "womanId": "MP_Gunrunning_Tattoo_025_F", "dlc": "mpgunrunning" },
        { "name": "Serpent Revolver", "file": "mp_gunrunning_tattoo_027", "manId": "MP_Gunrunning_Tattoo_027_M", "womanId": "MP_Gunrunning_Tattoo_027_F", "dlc": "mpgunrunning" },
        { "name": "Diamond Sparkle", "file": "mp_hip_tat_003", "manId": "FM_Hip_M_Tat_003", "womanId": "FM_Hip_F_Tat_003", "dlc": "mphipster" },
        { "name": "Bricks", "file": "mp_hip_tat_007", "manId": "FM_Hip_M_Tat_007", "womanId": "FM_Hip_F_Tat_007", "dlc": "mphipster" },
        { "name": "Mustache", "file": "mp_hip_tat_015", "manId": "FM_Hip_M_Tat_015", "womanId": "FM_Hip_F_Tat_015", "dlc": "mphipster" },
        { "name": "Lightning Bolt", "file": "mp_hip_tat_016", "manId": "FM_Hip_M_Tat_016", "womanId": "FM_Hip_F_Tat_016", "dlc": "mphipster" },
        { "name": "Pizza", "file": "mp_hip_tat_026", "manId": "FM_Hip_M_Tat_026", "womanId": "FM_Hip_F_Tat_026", "dlc": "mphipster" },
        { "name": "PadLock", "file": "mp_hip_tat_027", "manId": "FM_Hip_M_Tat_027", "womanId": "FM_Hip_F_Tat_027", "dlc": "mphipster" },
        { "name": "Thorny Rose", "file": "mp_hip_tat_028", "manId": "FM_Hip_M_Tat_028", "womanId": "FM_Hip_F_Tat_028", "dlc": "mphipster" },
        { "name": "Stop", "file": "mp_hip_tat_034", "manId": "FM_Hip_M_Tat_034", "womanId": "FM_Hip_F_Tat_034", "dlc": "mphipster" },
        { "name": "Sunrise", "file": "mp_hip_tat_037", "manId": "FM_Hip_M_Tat_037", "womanId": "FM_Hip_F_Tat_037", "dlc": "mphipster" },
        { "name": "Sleeve", "file": "mp_hip_tat_039", "manId": "FM_Hip_M_Tat_039", "womanId": "FM_Hip_F_Tat_039", "dlc": "mphipster" },
        { "name": "Triangle White", "file": "mp_hip_tat_043", "manId": "FM_Hip_M_Tat_043", "womanId": "FM_Hip_F_Tat_043", "dlc": "mphipster" },
        { "name": "Peace", "file": "mp_hip_tat_048", "manId": "FM_Hip_M_Tat_048", "womanId": "FM_Hip_F_Tat_048", "dlc": "mphipster" },
        { "name": "Piston Sleeve", "file": "mp_importexport_tat_004", "manId": "MP_MP_ImportExport_Tat_004_M", "womanId": "MP_MP_ImportExport_Tat_004_F", "dlc": "mpimportexport" },
        { "name": "Scarlett", "file": "mp_importexport_tat_008", "manId": "MP_MP_ImportExport_Tat_008_M", "womanId": "MP_MP_ImportExport_Tat_008_F", "dlc": "mpimportexport" },
        { "name": "No Evil", "file": "mp_lr_tat_005", "manId": "MP_LR_Tat_005_M", "womanId": "MP_LR_Tat_005_F", "dlc": "mplowrider" },
        { "name": "Love Hustle", "file": "mp_lr_tat_006", "manId": "MP_LR_Tat_006_M", "womanId": "MP_LR_Tat_006_F", "dlc": "mplowrider2" },
        { "name": "Skeleton Party", "file": "mp_lr_tat_018", "manId": "MP_LR_Tat_018_M", "womanId": "MP_LR_Tat_018_F", "dlc": "mplowrider2" },
        { "name": "My Crazy Life", "file": "mp_lr_tat_022", "manId": "MP_LR_Tat_022_M", "womanId": "MP_LR_Tat_022_F", "dlc": "mplowrider2" },
        { "name": "Los Santos Life", "file": "mp_lr_tat_027", "manId": "MP_LR_Tat_027_M", "womanId": "MP_LR_Tat_027_F", "dlc": "mplowrider" },
        { "name": "City Sorrow", "file": "mp_lr_tat_033", "manId": "MP_LR_Tat_033_M", "womanId": "MP_LR_Tat_033_F", "dlc": "mplowrider" },
        { "name": "Fatal Dagger", "file": "mp_luxe_tat_005", "manId": "MP_LUXE_TAT_005_M", "womanId": "MP_LUXE_TAT_005_F", "dlc": "mpluxe2" },
        { "name": "Floral Symmetry", "file": "mp_luxe_tat_009", "manId": "MP_LUXE_TAT_009_M", "womanId": "MP_LUXE_TAT_009_F", "dlc": "mpluxe" },
        { "name": "Egyptian Mural", "file": "mp_luxe_tat_016", "manId": "MP_LUXE_TAT_016_M", "womanId": "MP_LUXE_TAT_016_F", "dlc": "mpluxe2" },
        { "name": "Divine Goddess", "file": "mp_luxe_tat_018", "manId": "MP_LUXE_TAT_018_M", "womanId": "MP_LUXE_TAT_018_F", "dlc": "mpluxe2" },
        { "name": "Archangel & Mary", "file": "mp_luxe_tat_020", "manId": "MP_LUXE_TAT_020_M", "womanId": "MP_LUXE_TAT_020_F", "dlc": "mpluxe" },
        { "name": "Gabriel", "file": "mp_luxe_tat_021", "manId": "MP_LUXE_TAT_021_M", "womanId": "MP_LUXE_TAT_021_F", "dlc": "mpluxe" },
        { "name": "Python Skull", "file": "mp_luxe_tat_028", "manId": "MP_LUXE_TAT_028_M", "womanId": "MP_LUXE_TAT_028_F", "dlc": "mpluxe2" },
        { "name": "Geometric Design", "file": "mp_luxe_tat_031", "manId": "MP_LUXE_TAT_031_M", "womanId": "MP_LUXE_TAT_031_F", "dlc": "mpluxe2" },
        { "name": "Honor", "file": "mp_smuggler_tattoo_004", "manId": "MP_Smuggler_Tattoo_004_M", "womanId": "MP_Smuggler_Tattoo_004_F", "dlc": "mpsmuggler" },
        { "name": "Horrors Of The Deep", "file": "mp_smuggler_tattoo_008", "manId": "MP_Smuggler_Tattoo_008_M", "womanId": "MP_Smuggler_Tattoo_008_F", "dlc": "mpsmuggler" },
        { "name": "Mermaid's Curse", "file": "mp_smuggler_tattoo_014", "manId": "MP_Smuggler_Tattoo_014_M", "womanId": "MP_Smuggler_Tattoo_014_F", "dlc": "mpsmuggler" },
        { "name": "8 Eyed Skull", "file": "mp_stunt_tat_001", "manId": "MP_MP_Stunt_tat_001_M", "womanId": "MP_MP_Stunt_tat_001_F", "dlc": "mpstunt" },
        { "name": "Big Cat", "file": "mp_stunt_tat_002", "manId": "MP_MP_Stunt_tat_002_M", "womanId": "MP_MP_Stunt_tat_002_F", "dlc": "mpstunt" },
        { "name": "Moonlight Ride", "file": "mp_stunt_tat_008", "manId": "MP_MP_Stunt_tat_008_M", "womanId": "MP_MP_Stunt_tat_008_F", "dlc": "mpstunt" },
        { "name": "Piston Head", "file": "mp_stunt_tat_022", "manId": "MP_MP_Stunt_tat_022_M", "womanId": "MP_MP_Stunt_tat_022_F", "dlc": "mpstunt" },
        { "name": "Tanked", "file": "mp_stunt_tat_023", "manId": "MP_MP_Stunt_tat_023_M", "womanId": "MP_MP_Stunt_tat_023_F", "dlc": "mpstunt" },
        { "name": "Stuntman's End", "file": "mp_stunt_tat_035", "manId": "MP_MP_Stunt_tat_035_M", "womanId": "MP_MP_Stunt_tat_035_F", "dlc": "mpstunt" },
        { "name": "Kaboom", "file": "mp_stunt_tat_039", "manId": "MP_MP_Stunt_tat_039_M", "womanId": "MP_MP_Stunt_tat_039_F", "dlc": "mpstunt" },
        { "name": "Engine Arm", "file": "mp_stunt_tat_043", "manId": "MP_MP_Stunt_tat_043_M", "womanId": "MP_MP_Stunt_tat_043_F", "dlc": "mpstunt" }
    ]
}